staticconfig/__init__.py
staticconfig-0.0.6.dist-info/LICENSE
staticconfig-0.0.6.dist-info/METADATA
staticconfig-0.0.6.dist-info/WHEEL
staticconfig-0.0.6.dist-info/top_level.txt
staticconfig-0.0.6.dist-info/RECORD
