Metadata-Version: 2.1
Name: staticconfig
Version: 0.0.6
Summary: Json config files with a statically defined structure.
Home-page: https://github.com/gammelalf/staticconfig
Author: Wolfgang Fischer
Author-email: 31348226+gammelalf@users.noreply.github.com
License: UNKNOWN
Platform: UNKNOWN
Classifier: Programming Language :: Python :: 3
Classifier: License :: OSI Approved :: MIT License
Classifier: Operating System :: OS Independent
Requires-Python: >=3.5
